[
    {
        "title": "Top Flight Destinations",
        "list": [
            [
                "Flights to Da Nang",
                "Flights to Phu Quoc",
                "Flights to Nha Trang",
                "Flights to Hanoi",
                "Flights to Da Lat",
                "Flights to Hue"
            ],
            [
                "Flights from Sai Gon to Hanoi",
                "Flights from Sai Gon to Danang",
                "Flights from Sai Gon to Phu Quoc",
                "Flights from Sai Gon to Nha Trang",
                "Flights from Sai Gon to Da Lat",
                "Flights to Vinh"
            ],
            [
                "Flights from Hanoi to Sai Gon",
                "Flights from Hanoi to Phu Quoc",
                "Flights from Hanoi to Da Nang",
                "Flights from Ha Noi to Nha Trang",
                "Flights from Hanoi to Da Lat",
                "Flights to Hai Phong"
            ],
            [
                "Flights from Da Nang to Hanoi",
                "Flights from Da Nang to Sai Gon",
                "Flights from Sai Gon to Singapore",
                "Flights from Sai Gon to Bangkok",
                "Flights from Hanoi to Singapore",
                "Flights from Hanoi to Bangkok"
            ]
        ]
    },
    {
        "title": "Top Hotel Destinations",
        "list": [
            [
                "Nha Trang Hotels",
                "Ho Chi Minh Hotels",
                "Da Nang Hotels",
                "Sa Pa Hotels",
                "Phu Quoc Hotels"
            ],
            [
                "Da Lat Hotels",
                "Ha Noi Hotels",
                "Hoi An Hotels",
                "Thua Thien Hue Hotels",
                "Hai Phong Hotels"
            ],
            [
                "Halong Bay Hotels",
                "Mui Ne Hotels",
                "Phan Thiet Hotels",
                "Quy Nhon Hotels"
            ]
        ]
    },
    {
        "title": "Top Packages Destination",
        "list": [
            [
                "Things to do in Ho Chi Minh City",
                "Things to do in Hoi An",
                "Things to do in Da Nang",
                "Things to do in Nha Trang",
                "Things to do in Da Lat"
            ],
            [
                "Things to do in Hanoi",
                "Things to do in Phu Quoc",
                "Things to do in Sa Pa",
                "Things to do in Ha Giang",
                "Things to do in Ninh Binh"
            ],
            [
                "Things to do in Singapore",
                "Things to do in Thailand",
                "Things to do in Malaysia",
                "Things to do in Korea",
                "Things to do in Japan"
            ]
        ]
    },
    {
        "title": "Top Things to Do",
        "list": [
            [
                "Ho Chi Minh City Package",
                "Hanoi Package"
            ],
            [
                "Da Nang Package",
                "Singapore Package"
            ],
            [
                "Nha Trang Package",
                "Phu Quoc Package",
                "EPIC Sale",
                "EPIC Referral"
            ]
        ]
    }
]